{
  "global_id": 152,
  "species": "Eelektrik",
  "nature": "Hardy",
  "item": "Quick Claw",
  "moves": [
    "Thunderbolt",
    "Acid Spray",
    "Acrobatics",
    "Gastro Acid"
  ],
  "evs": "Atk/SpA",
  "variant_index": 1,
  "source_url": "https://www.smogon.com/ingame/bc/bw_subway_pokemon",
  "filename": "eelektrik1.json",
  "level": 50,
  "ivs": {
    "HP": 31,
    "Atk": 31,
    "Def": 31,
    "SpA": 31,
    "SpD": 31,
    "Spe": 31
  },
  "evs_numeric": {
    "HP": 0,
    "Atk": 255,
    "Def": 0,
    "SpA": 255,
    "SpD": 0,
    "Spe": 0
  },
  "stats_lv50": {
    "HP": 140,
    "Atk": 137,
    "Def": 90,
    "SpA": 127,
    "SpD": 90,
    "Spe": 60
  },
  "sprite_url_pokeapi": "https://raw.githubusercontent.com/PokeAPI/sprites/master/sprites/pokemon/603.png",
  "dex_number": 603,
  "item_sprite_url": "https://raw.githubusercontent.com/PokeAPI/sprites/master/sprites/items/quick-claw.png",
  "moves_meta": [
    {
      "name": "Thunderbolt",
      "slug": "thunderbolt",
      "type": "electric"
    },
    {
      "name": "Acid Spray",
      "slug": "acid-spray",
      "type": "poison"
    },
    {
      "name": "Acrobatics",
      "slug": "acrobatics",
      "type": "flying"
    },
    {
      "name": "Gastro Acid",
      "slug": "gastro-acid",
      "type": "poison"
    }
  ]
}