{
  "global_id": 752,
  "species": "Quagsire",
  "nature": "Careful",
  "item": "Leftovers",
  "moves": [
    "Curse",
    "Amnesia",
    "Earthquake",
    "Waterfall"
  ],
  "evs": "HP/SpD",
  "variant_index": 4,
  "source_url": "https://www.smogon.com/ingame/bc/bw_subway_pokemon",
  "filename": "quagsire4.json",
  "level": 50,
  "ivs": {
    "HP": 31,
    "Atk": 31,
    "Def": 31,
    "SpA": 31,
    "SpD": 31,
    "Spe": 31
  },
  "evs_numeric": {
    "HP": 255,
    "Atk": 0,
    "Def": 0,
    "SpA": 0,
    "SpD": 255,
    "Spe": 0
  },
  "stats_lv50": {
    "HP": 202,
    "Atk": 105,
    "Def": 105,
    "SpA": 76,
    "SpD": 128,
    "Spe": 55
  },
  "sprite_url_pokeapi": "https://raw.githubusercontent.com/PokeAPI/sprites/master/sprites/pokemon/195.png"
}